polyhorn/Coefficient.py
polyhorn/Constant.py
polyhorn/Constraint.py
polyhorn/Convertor.py
polyhorn/DNF.py
polyhorn/Farkas.py
polyhorn/Handelman.py
polyhorn/Parser.py
polyhorn/Polynomial.py
polyhorn/PositiveModel.py
polyhorn/Putinar.py
polyhorn/Solver.py
polyhorn/UnknownVariable.py
polyhorn/__init__.py
polyhorn/main.py
polyhorn-0.0.7.dist-info/LICENSE
polyhorn-0.0.7.dist-info/METADATA
polyhorn-0.0.7.dist-info/WHEEL
polyhorn-0.0.7.dist-info/top_level.txt
polyhorn-0.0.7.dist-info/RECORD
