Metadata-Version: 2.1
Name: polyhorn
Version: 0.0.7
Summary: PolyHorn is a solver for Polynomial Horn Clauses (PHC).
Author-email: Krishnendu Chatterjee <krishnendu.chatterjee@ist.ac.at>, Amir Kafshdar Goharshady <goharshady@cse.ust.hk>, Ehsan Kafshdar Goharshady <ehsan.goharshady@ist.ac.at>, Mehrdad Karrabi <mehrdad.karrabi@ist.ac.at>, Milad Saadat <milad.saadat@sharif.edu>, Maximilian Seeliger <maximilian.seeliger@tuwien.ac.at>, Djordje Zikelic <dzikelic@smu.edu.sg>
Project-URL: Homepage, https://github.com/ChatterjeeGroup-ISTA/PolyHorn/
Project-URL: Issues, https://github.com/ChatterjeeGroup-ISTA/PolyHorn/issues
Classifier: Programming Language :: Python :: 3
Classifier: License :: OSI Approved :: MIT License
Classifier: Operating System :: OS Independent
Requires-Python: >=3.9
License-File: LICENSE
Requires-Dist: numpy
Requires-Dist: lark
Requires-Dist: pysmt
